{
  "project_info": {
    "project_number": "644450403462",
    "project_id": "chasajo-12e3a",
    "storage_bucket": "chasajo-12e3a.appspot.com"
  },
  "client": [
    {
      "client_info": {
        "mobilesdk_app_id": "1:644450403462:android:7b8ec58ba5b689c0677d07",
        "android_client_info": {
          "package_name": "com.example.cha_sa_jo_flutter"
        }
      },
      "oauth_client": [
        {
          "client_id": "644450403462-qa4heoqthm1rgml34gvq3ju6iht7m1ip.apps.googleusercontent.com",
          "client_type": 3
        }
      ],
      "api_key": [
        {
          "current_key": "AIzaSyDM7BS1auRNdSK_MlsGI1RxIWGDQlHGRFA"
        }
      ],
      "services": {
        "appinvite_service": {
          "other_platform_oauth_client": [
            {
              "client_id": "644450403462-qa4heoqthm1rgml34gvq3ju6iht7m1ip.apps.googleusercontent.com",
              "client_type": 3
            }
          ]
        }
      }
    }
  ],
  "configuration_version": "1"
}